sessions/__init__.py
sessions/asyncsession.py
sessions/config.py
sessions/meta.py
sessions/objects.py
sessions/proxysession.py
sessions/session.py
sessions/thread.py
sessions/tor.py
sessions/useragents.py
sessions/utils.py
sessions/validators.py
sessions/vars.py
sessions/cache/__init__.py
sessions/cache/abstract.py
sessions/cache/pycache.py
sessions/cache/redis.py
sessions/cache/sqlite.py
sessions/ratelimit/__init__.py
sessions/ratelimit/abstract.py
sessions/ratelimit/pyratelimit.py
sessions/ratelimit/redis.py
sessions/ratelimit/sqlite.py
pysessions-0.1.1.dist-info/LICENSE
pysessions-0.1.1.dist-info/METADATA
pysessions-0.1.1.dist-info/WHEEL
pysessions-0.1.1.dist-info/top_level.txt
pysessions-0.1.1.dist-info/RECORD
