Metadata-Version: 2.1
Name: pysessions
Version: 0.1.1
Summary: A wrapper around popular python HTTP client providing enhanced features such as ratelimiting, caching, multiple requests
Author-email: John Gaddis <normlman@live.com>
Project-URL: Homepage, https://github.com/irjohn/pysessions
Classifier: Programming Language :: Python :: 3
Classifier: License :: OSI Approved :: GNU General Public License v3 or later (GPLv3+)
Classifier: Operating System :: Unix
Requires-Python: >=3.10
License-File: LICENSE
Requires-Dist: orjson
Requires-Dist: requests
Requires-Dist: httpx[http2] >=0.14.0
Requires-Dist: aiohttp[speedups] >=3.9
Requires-Dist: alive-progress
Requires-Dist: python-dotenv
Requires-Dist: yarl
Requires-Dist: redislite
Requires-Dist: redis
Provides-Extra: all
Requires-Dist: redislite ; extra == 'all'
Requires-Dist: stem ; extra == 'all'
Provides-Extra: backend
Requires-Dist: redislite ; extra == 'backend'
Provides-Extra: proxy
Requires-Dist: requests[socks] ; extra == 'proxy'
Provides-Extra: tor
Requires-Dist: stem ; extra == 'tor'
